scrapyx_bright_data/__init__.py
scrapyx_bright_data/bright_data.py
scrapyx_bright_data-0.1.2.dist-info/METADATA
scrapyx_bright_data-0.1.2.dist-info/WHEEL
scrapyx_bright_data-0.1.2.dist-info/top_level.txt
scrapyx_bright_data-0.1.2.dist-info/RECORD
