Metadata-Version: 2.1
Name: scrapyx-bright-data
Version: 0.1.2
Summary: Bright Data middleware for Scrapy
Home-page: https://github.com/tubndgit/scrapyx-bright-data
Author: Henry B.
Author-email: tubnd.younet@gmail.com
License: MIT
Download-URL: https://github.com/tubndgit/scrapyx-bright-data/archive/master.zip
Platform: UNKNOWN
Requires-Python: >=2.7
